chinillavdf.cpython-37m-x86_64-linux-gnu.so
chinillavdf.libs/libgmp-0b97008e.so.10.4.1
chinillavdf.libs/libgmpxx-faeb1ede.so.4.6.1
chinillavdf-1.0.9.dist-info/METADATA
chinillavdf-1.0.9.dist-info/top_level.txt
chinillavdf-1.0.9.dist-info/RECORD
chinillavdf-1.0.9.dist-info/WHEEL
chinillavdf-1.0.9.dist-info/LICENSE
