Metadata-Version: 2.1
Name: chinillavdf
Version: 1.0.9
Summary: Chinilla vdf verification (wraps C++)
Home-page: https://github.com/Chinilla/chinillavdf
Author: Edward Teach
Author-email: edward@chinilla.com
License: Apache License
Platform: UNKNOWN
Requires-Python: >=3.7
License-File: LICENSE
